[
  {
    "id": 1,
    "title": "Quiz Rock des années 70-80",
    "description": "Testez vos connaissances sur le rock classique des années 70 et 80.",
    "questions": [
      {
        "questionId": 101,
        "question": "Quel groupe a sorti 'Bohemian Rhapsody' en 1975 ?",
        "answers": [
          { "questionId": 101, "answerId": 1, "answerContent": "Queen" },
          { "questionId": 101, "answerId": 2, "answerContent": "The Beatles" },
          { "questionId": 101, "answerId": 3, "answerContent": "The Rolling Stones" }
        ],
        "correctAnswer": [
          { "questionId": 101, "answerId": 1, "answerContent": "Queen" }
        ],
        "hints": ["Le leader du groupe était Freddie Mercury"],
        "audioPath": "assets/musics/Michael Jackson - Billie Jean.mp3"
      },
      {
        "questionId": 102,
        "question": "Quel album des Pink Floyd est sorti en 1973 ?",
        "answers": [
          { "questionId": 102, "answerId": 4, "answerContent": "Dark Side of the Moon" },
          { "questionId": 102, "answerId": 5, "answerContent": "The Wall" },
          { "questionId": 102, "answerId": 6, "answerContent": "Wish You Were Here" }
        ],
        "correctAnswer": [
          { "questionId": 102, "answerId": 4, "answerContent": "Dark Side of the Moon" }
        ],
        "hints": ["La pochette de l'album représente un prisme"],
        "audioPath": "assets/musics/Michael Jackson - Billie Jean.mp3"
      },
      {
        "questionId": 103,
        "question": "Qui a chanté 'Hotel California' en 1976 ?",
        "answers": [
          { "questionId": 103, "answerId": 7, "answerContent": "The Eagles" },
          { "questionId": 103, "answerId": 8, "answerContent": "Fleetwood Mac" },
          { "questionId": 103, "answerId": 9, "answerContent": "Led Zeppelin" }
        ],
        "correctAnswer": [
          { "questionId": 103, "answerId": 7, "answerContent": "The Eagles" }
        ],
        "hints": ["Le groupe est connu pour son style country rock"],
        "audioPath": "assets/musics/Michael Jackson - Billie Jean.mp3"
      }
    ]
  },
  {
    "id": 2,
    "title": "Quiz Disco & Funk des années 70-80",
    "description": "Un quiz sur la musique dansante des années 70 et 80.",
    "questions": [
      {
        "questionId": 201,
        "question": "Qui a chanté 'Stayin' Alive' en 1977 ?",
        "answers": [
          { "questionId": 201, "answerId": 10, "answerContent": "Bee Gees" },
          { "questionId": 201, "answerId": 11, "answerContent": "Earth, Wind & Fire" },
          { "questionId": 201, "answerId": 12, "answerContent": "Kool & The Gang" }
        ],
        "correctAnswer": [
          { "questionId": 201, "answerId": 10, "answerContent": "Bee Gees" }
        ],
        "hints": ["Chanson emblématique du film 'Saturday Night Fever'"],
        "audioPath": "assets/musics/Michael Jackson - Billie Jean.mp3"
      },
      {
        "questionId": 202,
        "question": "Quel est le tube le plus célèbre de Michael Jackson en 1983 ?",
        "answers": [
          { "questionId": 202, "answerId": 13, "answerContent": "Beat It" },
          { "questionId": 202, "answerId": 14, "answerContent": "Billie Jean" },
          { "questionId": 202, "answerId": 15, "answerContent": "Thriller" }
        ],
        "correctAnswer": [
          { "questionId": 202, "answerId": 14, "answerContent": "Billie Jean" }
        ],
        "hints": ["Le clip montre le chanteur marcher sur des dalles lumineuses"],
        "audioPath": "assets/musics/Michael Jackson - Billie Jean.mp3"
      },
      {
        "questionId": 203,
        "question": "Quel groupe a chanté 'Le Freak' en 1978 ?",
        "answers": [
          { "questionId": 203, "answerId": 16, "answerContent": "Chic" },
          { "questionId": 203, "answerId": 17, "answerContent": "Village People" },
          { "questionId": 203, "answerId": 18, "answerContent": "Boney M." }
        ],
        "correctAnswer": [
          { "questionId": 203, "answerId": 16, "answerContent": "Chic" }
        ],
        "hints": ["Le refrain contient 'Freak out!'"],
        "audioPath": "assets/musics/Michael Jackson - Billie Jean.mp3"
      }
    ]
  }
]
